{
  "cancelOrder(): testCancelOrder": "52753",
  "fillLimitOrder(): testFillLimitOrderWithETH": "158029",
  "fillLimitOrder(): testFillWithBetterTakingAmount": "215471",
  "fillLimitOrder(): testFillWithBetterTakingAmountButGetAdjusted": "215705",
  "fillLimitOrder(): testFillWithETHRefund": "165308",
  "fillLimitOrder(): testFillWithLargerVolumeAndSettleAsManyAsPossible": "215693",
  "fillLimitOrder(): testFillWithoutMakerSigForVerifiedOrder": "215471",
  "fillLimitOrder(): testFillWithoutMakerSigForVerifiedOrder(without makerSig)": "120983",
  "fillLimitOrder(): testFullyFillLimitOrder": "215471",
  "fillLimitOrder(): testFullyFillLimitOrderUsingAMM": "235046",
  "fillLimitOrder(): testPartiallyFillLimitOrder": "215471",
  "fillLimitOrderFullOrKill(): testFillWithFOK": "215449",
  "fillLimitOrderGroup(): testGroupFillRingTrade": "291749",
  "fillLimitOrderGroup(): testGroupFillWithPartialWETHUnwrap": "277818",
  "fillLimitOrderGroup(): testGroupFillWithTakerPrefundETH": "198117",
  "fillLimitOrderGroup(): testGroupFillWithWETHUnwrap": "198117",
  "fillLimitOrderGroup(): testPartialFillLargeOrderWithSmallOrders": "265910",
  "testGroupFillWithProfit: fillLimitOrderGroup()": "225225"
}
